livesurf_sdk/__init__.py
livesurf_sdk/api.py
livesurf_sdk-1.0.0.dist-info/METADATA
livesurf_sdk-1.0.0.dist-info/WHEEL
livesurf_sdk-1.0.0.dist-info/top_level.txt
livesurf_sdk-1.0.0.dist-info/RECORD
