Metadata-Version: 2.4
Name: livesurf-sdk
Version: 1.0.0
Summary: Python SDK для LiveSurf API
Author-email: DecPro <decpro2009@gmail.com>
License: MIT
Project-URL: Homepage, https://github.com/DevAnlim/livesurf-sdk-python
Project-URL: Repository, https://github.com/DevAnlim/livesurf-sdk-python
Project-URL: Issues, https://github.com/DevAnlim/livesurf-sdk-python/issues
Requires-Python: >=3.8
Requires-Dist: requests>=2.31.0
